mariobros/__init__.py
mariobros/cli.py
mariobros/mario.py
mariobros/mariofile.py
mariobros-0.4.4.dist-info/LICENSE
mariobros-0.4.4.dist-info/METADATA
mariobros-0.4.4.dist-info/WHEEL
mariobros-0.4.4.dist-info/entry_points.txt
mariobros-0.4.4.dist-info/top_level.txt
mariobros-0.4.4.dist-info/RECORD
